monacelli_pylog_prefs/__init__.py
monacelli_pylog_prefs/cli.py
monacelli_pylog_prefs/logger.py
monacelli_pylog_prefs/monacelli_pylog_prefs.py
monacelli_pylog_prefs-0.13.0.dist-info/AUTHORS.rst
monacelli_pylog_prefs-0.13.0.dist-info/LICENSE
monacelli_pylog_prefs-0.13.0.dist-info/METADATA
monacelli_pylog_prefs-0.13.0.dist-info/WHEEL
monacelli_pylog_prefs-0.13.0.dist-info/entry_points.txt
monacelli_pylog_prefs-0.13.0.dist-info/top_level.txt
monacelli_pylog_prefs-0.13.0.dist-info/RECORD
